httpx_negotiate_sspi/__init__.py
httpx_negotiate_sspi/py.typed
httpx_negotiate_sspi/sspi.py
httpx_negotiate_sspi-0.28.1.dist-info/METADATA
httpx_negotiate_sspi-0.28.1.dist-info/WHEEL
httpx_negotiate_sspi-0.28.1.dist-info/RECORD
