Metadata-Version: 2.1
Name: httpx-negotiate-sspi
Version: 0.28.1
Summary: SSPI authentication for httpx
Home-page: https://github.com/rob-blackbourn/httpx-negotiate-sspi
License: Apache-2.0
Author: Rob Blackbourn
Author-email: rob.blackbourn@gmail.com
Requires-Python: >=3.8,<4.0
Classifier: License :: OSI Approved :: Apache Software License
Classifier: Programming Language :: Python :: 3
Classifier: Programming Language :: Python :: 3.8
Classifier: Programming Language :: Python :: 3.9
Classifier: Programming Language :: Python :: 3.10
Classifier: Programming Language :: Python :: 3.11
Requires-Dist: httpx (>0.16,<0.29)
Requires-Dist: pywin32 (>=223)
Project-URL: Repository, https://github.com/rob-blackbourn/httpx-negotiate-sspi
